gitlabgroups/__init__.py
gitlabgroups/glclone.py
gitlabgroups/glfromsvn.py
gitlabgroups/glpull.py
gitlabgroups/glupload.py
gitlabgroups-0.7.1.data/scripts/glclone
gitlabgroups-0.7.1.data/scripts/glfromsvn
gitlabgroups-0.7.1.data/scripts/glpull
gitlabgroups-0.7.1.data/scripts/glupload
gitlabgroups-0.7.1.dist-info/LICENSE
gitlabgroups-0.7.1.dist-info/METADATA
gitlabgroups-0.7.1.dist-info/WHEEL
gitlabgroups-0.7.1.dist-info/top_level.txt
gitlabgroups-0.7.1.dist-info/RECORD
