Metadata-Version: 2.1
Name: gitlabgroups
Version: 0.7.1
Summary: Nexus Data writer implemented as a Tango Server
Home-page: https://github.com/nexdatas/writer
Author: Jan Kotanski
Author-email: jankotan@gmail.com
License: GNU GENERAL PUBLIC LICENSE v3
Keywords: gitlab subgroups clone pull all
Classifier: Development Status :: 5 - Production/Stable
Classifier: Intended Audience :: Science/Research
Classifier: Topic :: Scientific/Engineering :: Physics
Classifier: Topic :: Software Development :: Libraries :: Python Modules
Classifier: License :: OSI Approved :: GNU General Public License v3 (GPLv3)
Classifier: Programming Language :: Python :: 3
Classifier: Programming Language :: Python :: 3.4
Classifier: Programming Language :: Python :: 3.5
Classifier: Programming Language :: Python :: 3.6
Classifier: Programming Language :: Python :: 3.7
License-File: LICENSE
Requires-Dist: fabio
Requires-Dist: lxml
Requires-Dist: numpy (>1.6.0)
Requires-Dist: nxstools
Requires-Dist: pytz
